napari_serialcellpose/__init__.py
napari_serialcellpose/_version.py
napari_serialcellpose/folder_list_widget.py
napari_serialcellpose/napari.yaml
napari_serialcellpose/serial_analysis.py
napari_serialcellpose/serial_widget.py
napari_serialcellpose/utils.py
napari_serialcellpose/_tests/__init__.py
napari_serialcellpose/_tests/my_options.yml
napari_serialcellpose/_tests/test_widget.py
napari_serialcellpose/_tests/data/multifile/tile_0_0.tif
napari_serialcellpose/_tests/data/multifile/tile_0_1.tif
napari_serialcellpose/_tests/data/multifile/tile_1_0.tif
napari_serialcellpose/_tests/data/multifile/tile_1_1.tif
napari_serialcellpose/_tests/data/single_file_multichannel/sample_EmbryoTorax.tif
napari_serialcellpose/_tests/data/single_file_singlechannel/sample_EmbryoTorax_cells.tif
napari_serialcellpose/_tests/data/singlefile_singlechannel/sample_EmbryoTorax_cells.tif
napari_serialcellpose-0.4.0.dist-info/licenses/LICENSE
napari_serialcellpose-0.4.0.dist-info/METADATA
napari_serialcellpose-0.4.0.dist-info/WHEEL
napari_serialcellpose-0.4.0.dist-info/entry_points.txt
napari_serialcellpose-0.4.0.dist-info/top_level.txt
napari_serialcellpose-0.4.0.dist-info/RECORD
