Metadata-Version: 2.4
Name: napari-serialcellpose
Version: 0.4.0
Summary: A simple plugin to batch segment cells with cellpose
Home-page: https://github.com/guiwitz/napari-serialcellpose
Author: Guillaume Witz
Author-email: guillaume.witz@unibe.ch
License: BSD-3-Clause
Project-URL: Bug Tracker, https://github.com/guiwitz/napari-serialcellpose/issues
Project-URL: Documentation, https://github.com/guiwitz/napari-serialcellpose#README.md
Project-URL: Source Code, https://github.com/guiwitz/napari-serialcellpose
Project-URL: User Support, https://github.com/guiwitz/napari-serialcellpose/issues
Classifier: Development Status :: 2 - Pre-Alpha
Classifier: Intended Audience :: Developers
Classifier: Framework :: napari
Classifier: Topic :: Software Development :: Testing
Classifier: Programming Language :: Python
Classifier: Programming Language :: Python :: 3
Classifier: Programming Language :: Python :: 3.10
Classifier: Programming Language :: Python :: 3.11
Classifier: Programming Language :: Python :: 3.12
Classifier: Operating System :: OS Independent
Classifier: License :: OSI Approved :: BSD License
Requires-Python: >=3.10
License-File: LICENSE
Requires-Dist: cellpose
Requires-Dist: numpy
Requires-Dist: magicgui
Requires-Dist: qtpy
Requires-Dist: matplotlib
Requires-Dist: bioio
Requires-Dist: bioio-tifffile
Provides-Extra: testing
Requires-Dist: tox; extra == "testing"
Requires-Dist: pytest; extra == "testing"
Requires-Dist: pytest-cov; extra == "testing"
Requires-Dist: pytest-qt; extra == "testing"
Requires-Dist: napari; extra == "testing"
Requires-Dist: pyqt5; extra == "testing"
Requires-Dist: cellpose<4; extra == "testing"
Dynamic: license-file
